README.rst
setup.py
pyivi/__init__.py
pyivi/choices.py
pyivi/common.py
pyivi.egg-info/PKG-INFO
pyivi.egg-info/SOURCES.txt
pyivi.egg-info/dependency_links.txt
pyivi.egg-info/top_level.txt
pyivi/ivic/__init__.py
pyivi/ivic/definesivifgen.py
pyivi/ivic/definesiviscope.py
pyivi/ivic/definesivispecan.py
pyivi/ivic/ivi_defines.py
pyivi/ivic/ivicwrapper.py
pyivi/ivic/ivifgen.py
pyivi/ivic/iviscope.py
pyivi/ivic/ivispecan.py
pyivi/ivicom/__init__.py
pyivi/ivicom/agna.py
pyivi/ivicom/ivicomwrapper.py
pyivi/ivicom/iviscope.py
pyivi/ivicom/ivispecan.py
pyivi/ivifactory/__init__.py