Metadata-Version: 1.1
Name: pyivi
Version: 0.0.8
Summary: Control of data acquisition with remote instruments using 
Home-page: https://github.com/SamuelDeleglise/pyinstruments
Author: Samuel Deleglise
Author-email: samuel.deleglise@gmail.com
License: BSD
Keywords: instruments data-acquisition IVI interface
Platform: UNKNOWN
Classifier: Development Status :: 3 - Alpha
Classifier: Topic :: Scientific/Engineering :: Human Machine Interfaces
Classifier: License :: OSI Approved :: BSD License
